{"/N5aF7gR216Q90RN/Csm8g==":"frame-49.png","uNg/rZsnrfBzlQY/r+g6mg==":"mae-mu-xtrl02zuzxe-unsplash.jpg","3LVnfsLx8kl6oxYj7rpjDA==":"kevin-cloney-2zak5fp-p3o-unsplash.jpg","Yn09DldbgJ/yjp8iXxTHkg==":"pawel-czerwinski-ywiowhvrbvu-unsplash.jpg","s7EhEEN2by/KVCWK/ZmJ8w==":"daniela-diaz-u0lqnabx2he-unsplash.jpg","pdEiofDqWPvrDZftBf7OeQ==":"milad-fakurian-wnshbf-btbo-unsplash.jpg","djb2qbT3QKn2F7AdMAmIFQ==":"creator-2.png","w870wSnM/Do1YUrTkQMqWQ==":"creator-1.png","0OIw3RC0u73LGSNHIvk/vw==":"creator-portfolio.png","cAMx4wQJ+rh7UzXBdez6Sw==":"leilani-angel-k84vnnzxmtq-unsplash-cr.jpg","+ASp0Q6eoQGu26QQOA8SvQ==":"simon-lee-ynmpy1mlwms-unsplash.jpeg","WiQ59BGKzCyvdpq4JhEfPQ==":"milad-fakurian-pjg-sxdkpwq-unsplash-cr.jpg","+NQf6rEl6/eoTPi93iEj9A==":"milad-fakurian-bmsa5-tlfao-unsplash.jpg","yb6xHVi4NWTdV+D5N/SUKA==":"pawel-czerwinski-5kbadjivruc-unsplash1.jpg","XZ0x/sVOY2qDFMeipJyijA==":"gallery1.jpg","Lf/WoVi5L3Qnp6b23+MiVQ==":"gallery2.jpg","9F2RI94x1lAYvHz8QWyhHg==":"gallery3.jpg","xG7DVvXBC1Fmf5QXEl1FSA==":"gallery4.jpg","RiI4xwAZbTgeiHYklAjRhQ==":"gallery5.jpg","oxHqLzMeFvuCE9s/7onulw==":"gallery6.jpg","YQmv+gmgkTMVfi5ltjpaQA==":"gallery7.jpg","+dY6x6tL4GrzFaK5K1Ldiw==":"gallery8.jpg","sb1ebvdGD6YjhV3q5LcXDQ==":"logo1.png","XzvYanrvNf6uV5iBsDaqhA==":"logo2.png","k3Kh7npmUp7c3OImhp6I2A==":"leilani-angel-k84vnnzxmtq-unsplash-cr-1.jpg","NGsyS4dD3jVe9JNDhKMcNA==":"screenshot%202023-10-04%20at%2011.42.58%20pm-259x128.png","MQ1dc+DoTRVYzq0E/POOoQ==":"screenshot%202023-10-04%20at%2011.42.58%20pm-259x128.png","2m7e/K783CiNClAoA5sgMg==":"screenshot%202023-10-05%20at%2012.13.20%20am-1052x531.png","wAPZyQ7sU5gPMi/sicHV4Q==":"mbr-1200x794.jpg","ruhKFLretlMUG0cQANR3hQ==":"mbr-1600x1067.jpg","t8E6BqPPtdReodj9Jjodeg==":"mbr-1920x1816.png","BiojPegHZjWztoO/u+7nAQ==":"mbr-598x398.jpg","0Q+mWnzKDtOjQDFNfH4DvQ==":"mbr-598x398.jpeg","aKvMaswjAYN3/H9ByM0KmA==":"mbr-1-598x398.jpeg","2UaOz2lE4fgApp3yM3XrSA==":"mbr-376x259.jpg","t59/8DnwHGXQFXaB49FbFg==":"mbr-376x282.jpg","KkG2ZYWkEtnKEbQZO6FfvQ==":"mbr-376x251.jpg","2OjjI86Y8NE1PcAbWw9DbA==":"shameer-2268x3024.jpg","JdPMKUuHUnB2ikYX9r2cUw==":"abu-561x748.jpg","+SK6Va4h9x6vN9/dpc5FVg==":"pheonix-316x221.png","GKlvrQHJOsbCv9oXJr5Vuw==":"poseidon-316x222.png","UUFriB/XNE4sXwUTVU7Yrw==":"golem-316x228.png","QbBzQEab+eF/defR1xlfsA==":"shameer-2268x3024.jpeg","HsjDYvM3Oi74eN9qQvZnJg==":"abu-561x748.jpeg","q9MqZcvsA4djjDnW2vrdfw==":"arif%20temporary-696x958.png","FUx6tT9QHZdJX+QDDnAgCQ==":"hafiz-696x928.jpeg","DHbrvvg5u3LfDM6VW8MTjA==":"hafiz-1-696x928.jpeg","9jmrkwvt3hvElz6BlxdXRA==":"hafiz-2-696x928.jpeg","h1oL2w0RxYHyt9dxVGJWTA==":"hafiz-3-696x928.jpeg","Znf3aa9yz9J/SzvJrntxUQ==":"syafiq-561x748.jpg","05Iyt5IOk6EgMctH8d3bsw==":"syafiq-561x748.jpeg","AlZCD6dq0EmAF9dDhp0WJw==":"syafiq-1-561x748.jpeg","09d8dWFf+Ji2R0f8aVAeFg==":"syafiq-2-561x748.jpeg","Xq/LpQoHRzZu+mCahxDkHw==":"20231108-121206-561x997.jpeg","r16lDsE3aO1HUkFxGv0GQQ==":"20231108-121207-561x997.jpeg","TyjKsSy8KFHHMkZ4HlOG2w==":"mbr-1920x1078.jpg","gbzinA2dw9NHamF1MzNeGA==":"osomlogo-1.png","uMCFq/7mrxjiC/k18OF3sA==":"arif-temporary.png","z1EH7RTq+2RMwIzT/e2MtA==":"hafiz.jpg","/OlKMlaoABuTO4M/cKnjZw==":"hafiz.jpeg","+6wqlpHws1gFWloaprKr7g==":"sofyank.jpg","dkknIo5MwlvDIkiVlTgIxw==":"sofyank.jpeg","91pYijM0+Q2qgQeesap1JA==":"sofyank-1.jpeg","HYjg2ziuM8hedoaXZLSZGg==":"sofyank-2.jpeg","we64QvlYrN8uKB4fcwDoaA==":"osomlogo-261x101.png","JBIOmjZxa5eZuxLi3ibY4Q==":"screenshot-2023-10-05-at-12.13.20-am-1052x531.webp","lnWgRgX0rXpz0DE/oVhCJg==":"mbr-1600x1067.webp","05RFI2qLLhgunoyKwUP7+A==":"mbr-1200x794.webp","5BCTszUB8M3/Z3PkNTMVEg==":"pheonix-316x222.png","rV9uRELGgTDbmvg9Zkm6JQ==":"logo-rumah(phoenix_1)-316x316.png","Nj5uaZ2ZxgCd21CYfhw00Q==":"logo-rumah(poseidon_1)-316x316.png","O5KNwHhBPUr8ugtzi8+pkg==":"logo-rumah(golem_1)-316x316.png","9UsA0uo6tz29VOa6+/thaw==":"arif%20temporary-400x551.png","dlMKfCYFGWbRis++RDQfQw==":"hafiz-400x533.jpg","8c4zGHQAK00WhKREQKiwRA==":"hafiz-400x533.jpeg","yFF5tAFONz6TiSU8tbKDJA==":"sofyank-400x400.jpeg","vXXqGnN0PIc2qMevP75P2A==":"sofyank-1-400x400.jpeg","dJtG8hY+Fdm6wi+DTpEHig==":"shameer-561x748.jpg","axPVtlL6T9WGXQ9D8OsYKw==":"shameer-561x748.jpeg","Y6vlhHsUNlM0UyZoU46SmQ==":"shameer-1-561x748.jpeg","gkb0yvK1t7wxoc+x7DkofA==":"whatsapp%20image%202023-11-14%20at%208.33.55%20am-561x748.jpg","i14Kw5RWf1izUQJCNQ7H9A==":"whatsapp%20image%202023-11-14%20at%208.33.55%20am-561x748.jpeg","iWiYrKJbI1DiQVa+YnPxcQ==":"20231108-121206-561x997.jpeg","PXH8WNsxq4nJOgMm2sPLrA==":"20231108-121207-561x997.jpeg","vi0wngJUZgQWr1BwasmqBw==":"20231108-121208-561x997.jpeg","N6/UtuJbXLJ/ERuonHzkRg==":"mbr-1920x1078.webp","cN78o7MA8z3mbcR+ioBidA==":"shameer-1-357x421.jpg","Yjg/+VwPUvhtwR/1EIvEnA==":"abu-1-561x748.jpg","88qixm8QHhTK/tXYikXw5w==":"whatsapp%20image%202023-11-14%20at%208.33.55%20am-561x748.jpg","qxD+4d+RcbBrIseBG2j8lg==":"20231108-121207-358x442.jpg","8qr5HgB7fQSQP2ChgAMiVw==":"arif-temporary.webp","Jrmdf6UsKydVOW1YZLhAcA==":"arif%20temporary-280x386.png","UGPKbc7NOSW2AIHtWccUfA==":"hafiz-164x218.jpg","I1g3RPP8fAkIT3ycAou1Xg==":"hafiz.webp","gYnyAY5ItXmmGIx/ZpxBVA==":"sofyank-280x350.jpg","DZVgYy8x+MYYinznp6yN2Q==":"osomlogo%20-%20copy-393x422.png","V5pPxcC48hzbN8YdL7Fpew==":"osomlogo%20-%20copy-393x422.png","/VfUCiHJ7FE3V9clg9V2Zg==":"osomlogo-393x151.png","TqEtUq0xbN8ocDtF9RqjxA==":"mbr-1920x1357.jpg","sdZuKMilDPSpi5ZEC1J1EA==":"osomlogo-1884x726.png"}